deterministic_zip/__init__.py
deterministic_zip-0.1.dist-info/LICENSE.txt
deterministic_zip-0.1.dist-info/METADATA
deterministic_zip-0.1.dist-info/WHEEL
deterministic_zip-0.1.dist-info/entry_points.txt
deterministic_zip-0.1.dist-info/top_level.txt
deterministic_zip-0.1.dist-info/RECORD
