Metadata-Version: 2.1
Name: deterministic-zip
Version: 0.1
Summary: A program to create deterministic zip files.
Home-page: https://github.com/bboe/deterministic_zip
Author: Bryce Boe
Author-email: bbzbryce@gmail.com
License: Simplified BSD License
Keywords: aws lambda zip
Platform: UNKNOWN
Classifier: Intended Audience :: Developers
Classifier: License :: OSI Approved :: BSD License
Classifier: Programming Language :: Python :: 3.7
